lambda_multiprocessing/__init__.py
lambda_multiprocessing/main.py
lambda_multiprocessing/py.typed
lambda_multiprocessing/test_main.py
lambda_multiprocessing/timeout.py
lambda_multiprocessing-1.1.dist-info/licenses/LICENSE.txt
lambda_multiprocessing-1.1.dist-info/METADATA
lambda_multiprocessing-1.1.dist-info/WHEEL
lambda_multiprocessing-1.1.dist-info/top_level.txt
lambda_multiprocessing-1.1.dist-info/RECORD
