Metadata-Version: 2.4
Name: lambda_multiprocessing
Version: 1.1
Summary: drop-in replacement for multiprocessing.Pool in AWS Lambda functions (without /dev/shm shared memory)
Home-page: https://github.com/mdavis-xyz/lambda_multiprocessing
Author: Matthew Davis
Author-email: github@mdavis.xyz
Keywords: python,AWS,Amazon,Lambda,multiprocessing,pool,concurrency
Classifier: Development Status :: 3 - Alpha
Classifier: Intended Audience :: Developers
Classifier: Operating System :: OS Independent
Classifier: License :: OSI Approved :: MIT License
Classifier: Programming Language :: Python :: 3
Classifier: Programming Language :: Python :: 3.9
Classifier: Programming Language :: Python :: 3.10
Classifier: Programming Language :: Python :: 3.11
Classifier: Programming Language :: Python :: 3.12
Classifier: Programming Language :: Python :: 3.13
License-File: LICENSE.txt
Dynamic: author
Dynamic: author-email
Dynamic: classifier
Dynamic: description
Dynamic: description-content-type
Dynamic: home-page
Dynamic: keywords
Dynamic: license-file
Dynamic: summary
